odoo/addons/stock_quant_expiration_date_tree/README.rst
odoo/addons/stock_quant_expiration_date_tree/__init__.py
odoo/addons/stock_quant_expiration_date_tree/__manifest__.py
odoo/addons/stock_quant_expiration_date_tree/i18n/es.po
odoo/addons/stock_quant_expiration_date_tree/i18n/stock_quant_expiration_date_tree.pot
odoo/addons/stock_quant_expiration_date_tree/models/__init__.py
odoo/addons/stock_quant_expiration_date_tree/models/stock_quant.py
odoo/addons/stock_quant_expiration_date_tree/readme/CONTRIBUTORS.rst
odoo/addons/stock_quant_expiration_date_tree/readme/DESCRIPTION.rst
odoo/addons/stock_quant_expiration_date_tree/static/description/icon.png
odoo/addons/stock_quant_expiration_date_tree/static/description/index.html
odoo/addons/stock_quant_expiration_date_tree/views/stock_quant.xml
odoo13_addon_stock_quant_expiration_date_tree-13.0.1.0.1.dev5.dist-info/METADATA
odoo13_addon_stock_quant_expiration_date_tree-13.0.1.0.1.dev5.dist-info/WHEEL
odoo13_addon_stock_quant_expiration_date_tree-13.0.1.0.1.dev5.dist-info/top_level.txt
odoo13_addon_stock_quant_expiration_date_tree-13.0.1.0.1.dev5.dist-info/RECORD
